g_bot/__init__.py
g_bot/cli.py
g_bot/config.ini
g_bot/main.py
gdrive_bot-1.0.6.dist-info/LICENSE
gdrive_bot-1.0.6.dist-info/METADATA
gdrive_bot-1.0.6.dist-info/WHEEL
gdrive_bot-1.0.6.dist-info/entry_points.txt
gdrive_bot-1.0.6.dist-info/top_level.txt
gdrive_bot-1.0.6.dist-info/RECORD
