Metadata-Version: 2.1
Name: gdrive-bot
Version: 1.0.6
Summary: upload files to gdrive with access token
Home-page: https://github.com/jakbin/g-bot
Author: Jak Bin
Author-email: jakbin4747@gmail.com
Project-URL: Bug Tracker, https://github.com/jakbin/g-bot/issues
Keywords: gdrive,g-bot,gdrive-api,gdrive-api-bot,gdrive-file-upload,gdrive-upload
Classifier: Programming Language :: Python :: 3.6
Classifier: License :: OSI Approved :: MIT License
Classifier: Natural Language :: English
Classifier: Operating System :: OS Independent
Requires-Python: >=3
License-File: LICENSE
Requires-Dist: tqdm
Requires-Dist: requests
Requires-Dist: requests-toolbelt
